archer_cli/__init__.py
archer_cli/ascii_logo.py
archer_cli/cli.py
archer_cli/run.py
archer_cli/tools_registry.py
archer_cli/cli/tools/registry.py
archer_cli/commands/__init__.py
archer_cli/commands/clear.py
archer_cli/commands/help.py
archer_cli/commands/ignore.py
archer_cli/commands/init.py
archer_cli/commands/stats.py
archer_cli/commands/status.py
archer_cli/tools/__init__.py
archer_cli/tools/exec.py
archer_cli/tools/fs.py
archer_cli/tools/search.py
archer_cli/tools/todo.py
archer_cli/tools/webfetch.py
archer_cli/utils/__init__.py
archer_cli/utils/ignore_manager.py
archer_cli/utils/token_manager.py
archer_cli-0.2.3.dist-info/licenses/LICENSE
archer_cli-0.2.3.dist-info/METADATA
archer_cli-0.2.3.dist-info/WHEEL
archer_cli-0.2.3.dist-info/entry_points.txt
archer_cli-0.2.3.dist-info/top_level.txt
archer_cli-0.2.3.dist-info/RECORD
